{
  "status": "completed",
  "task_number": 10,
  "session_id": "sess_1780081000_c525c7",
  "summary_path": "specs/010_implement_patternkey_feature_extractor_in_python/summaries/01_patternkey-summary.md",
  "files_created": [
    "src/bimodal_harness/schema/features.py",
    "tests/test_schema/test_features.py"
  ],
  "files_modified": [
    "src/bimodal_harness/schema/__init__.py"
  ],
  "tests_passed": true,
  "test_count": 41,
  "phases_completed": 3,
  "deviations": [
    "Research report test vectors 4 and 5 had incorrect complexity values (listed 4, correct is 5); implementation follows Lean source exactly",
    "mypy not available in environment; type checking via ruff + import verification instead"
  ]
}
